Metadata-Version: 1.1
Name: vicore
Version: 0.1.4
Summary: vial-core (vicore), a reusable vial architecture core module
Home-page: https://github.com/toranova/vicoreibase/
Author: Chia Jason
Author-email: chia_jason96@live.com
License: MIT
Download-URL: https://github.com/ToraNova/vicoreibase/archive/refs/tags/v0.1.4.tar.gz
Keywords: Flask
Platform: UNKNOWN
Classifier: Development Status :: 3 - Alpha
Classifier: Programming Language :: Python :: 3
Classifier: License :: OSI Approved :: MIT License
Classifier: Operating System :: OS Independent
Classifier: Intended Audience :: Developers
Classifier: License :: OSI Approved :: MIT License
Classifier: Programming Language :: Python :: 3
Classifier: Programming Language :: Python :: 3.6
Classifier: Programming Language :: Python :: 3.7
Classifier: Programming Language :: Python :: 3.8
